{
  "language": "fr",
  "title": "nos produits",
  "content_list": [
    {
      "type": "hero_content",
      "text": "Découvrez notre gamme de produits et services.",
      "headline": "nos produits"
    },
    {
      "type": "products_content",
      "alt_text": "Victoria Analytica",
      "image_url": "https://itrawsorigin.s3.ca-central-1.amazonaws.com/itraws2020assets/UI/Branding/product-logo.png",
      "image_display": true,
      "image": "/images/uploads/screenshot_2020-06-18-create-a-palette-coolors.png"
    }
  ]
}